mariem/REQUIREMENTS
mariem/VERSION
mariem/__init__.py
mariem/pandas.py
mariem-0.1.1.dist-info/LICENSE
mariem-0.1.1.dist-info/METADATA
mariem-0.1.1.dist-info/WHEEL
mariem-0.1.1.dist-info/top_level.txt
mariem-0.1.1.dist-info/RECORD
