Metadata-Version: 2.1
Name: mariem
Version: 0.1.1
Summary: Marie Magic Functions
Home-page: https://github.com/MatthiasRieck/mariem
Author: Matthias Rieck
Author-email: Matthias.Rieck@tum.de
License-File: LICENSE
Requires-Dist: pandas
